transsnet_afnews_3rd/__init__.py
transsnet_afnews_3rd/comprehend/__init__.py
transsnet_afnews_3rd/comprehend/classify.py
transsnet_afnews_3rd/comprehend/s3driver.py
transsnet_afnews_3rd-1.0.0.dev2.dist-info/METADATA
transsnet_afnews_3rd-1.0.0.dev2.dist-info/WHEEL
transsnet_afnews_3rd-1.0.0.dev2.dist-info/top_level.txt
transsnet_afnews_3rd-1.0.0.dev2.dist-info/RECORD
