Metadata-Version: 2.1
Name: transsnet-afnews-3rd
Version: 1.0.0.dev2
Summary: africa news third party project
Home-page: https://git.ms.netease.com/africaNews/transsnet_afnews_3rd
Author: UNKNOWN
Author-email: UNKNOWN
License: UNKNOWN
Platform: UNKNOWN
